digger/__init__.py
digger/blastresults_to_csv.py
digger/calc_motifs.py
digger/cirelli_contig_matches.py
digger/cirelli_to_fasta.py
digger/compare_annotations.py
digger/dig_sequence.py
digger/dig_utils.py
digger/digger.py
digger/find_alignments.py
digger/motif.py
digger/parse_genes.py
digger/parse_imgt_annotations.py
digger/search_motifs.py
digger/setup_motif_params.py
digger/slugify.py
digger/motifs/human/IGH/3'D-HEPTAMER_prob.csv
digger/motifs/human/IGH/3'D-NONAMER_prob.csv
digger/motifs/human/IGH/5'D-HEPTAMER_prob.csv
digger/motifs/human/IGH/5'D-NONAMER_prob.csv
digger/motifs/human/IGH/J-HEPTAMER_prob.csv
digger/motifs/human/IGH/J-NONAMER_prob.csv
digger/motifs/human/IGH/L-PART1_1_48_prob.csv
digger/motifs/human/IGH/L-PART1_2_48_prob.csv
digger/motifs/human/IGH/L-PART1_3_48_prob.csv
digger/motifs/human/IGH/L-PART1_4_48_prob.csv
digger/motifs/human/IGH/L-PART1_5_51_prob.csv
digger/motifs/human/IGH/L-PART1_6_63_prob.csv
digger/motifs/human/IGH/L-PART2_1_11_prob.csv
digger/motifs/human/IGH/OCTAMER_prob.csv
digger/motifs/human/IGH/V-HEPTAMER_prob.csv
digger/motifs/human/IGH/V-NONAMER_prob.csv
digger/motifs/human/IGH/conserved_motifs.fasta
digger/motifs/human/IGH/motif_params.json
digger/motifs/human/IGK/J-HEPTAMER_prob.csv
digger/motifs/human/IGK/J-NONAMER_prob.csv
digger/motifs/human/IGK/L-PART1_1_48_prob.csv
digger/motifs/human/IGK/L-PART1_2_57_prob.csv
digger/motifs/human/IGK/L-PART1_3_51_prob.csv
digger/motifs/human/IGK/L-PART1_4_51_prob.csv
digger/motifs/human/IGK/L-PART1_5_51_prob.csv
digger/motifs/human/IGK/L-PART1_6_51_prob.csv
digger/motifs/human/IGK/L-PART1_prob.csv
digger/motifs/human/IGK/L-PART2_1_11_prob.csv
digger/motifs/human/IGK/L-PART2_prob.csv
digger/motifs/human/IGK/OCTAMER_prob.csv
digger/motifs/human/IGK/V-HEPTAMER_prob.csv
digger/motifs/human/IGK/V-NONAMER_prob.csv
digger/motifs/human/IGK/conserved_motifs.fasta
digger/motifs/human/IGK/motif_params.json
digger/motifs/human/IGL/J-HEPTAMER_prob.csv
digger/motifs/human/IGL/J-NONAMER_prob.csv
receptor_digger-0.8.2.dist-info/licenses/license.txt
receptor_digger-0.8.2.dist-info/METADATA
receptor_digger-0.8.2.dist-info/WHEEL
receptor_digger-0.8.2.dist-info/entry_points.txt
receptor_digger-0.8.2.dist-info/top_level.txt
receptor_digger-0.8.2.dist-info/RECORD
