Metadata-Version: 2.4
Name: receptor_digger
Version: 0.8.2
Summary: Tools for de novo discovery of genomic germline IG and TR receptor sequences
Home-page: https://github.com/williamdlees/digger
Author: William Lees
Author-email: william@lees.org.uk
License: EUPL-1.2
Project-URL: Bug Tracker, https://github.com/williamdlees/digger/issues
Classifier: Programming Language :: Python :: 3
Classifier: Operating System :: OS Independent
Requires-Python: >=3.9
License-File: license.txt
Requires-Dist: biopython>=1.81
Requires-Dist: receptor_utils>=0.0.46
Requires-Dist: matplotlib-venn
Dynamic: license-file
